src/__init__.py
src/solarhouse/__init__.py
src/solarhouse/building.py
src/solarhouse/calculation.py
src/solarhouse/export.py
src/solarhouse/helpers.py
src/solarhouse/settings.py
src/solarhouse/setup.py
src/solarhouse/thermal_element.py
src/solarhouse/thermal_model.py
src/solarhouse/thermal_process.py
py_solarhouse-0.0.1.dist-info/METADATA
py_solarhouse-0.0.1.dist-info/WHEEL
py_solarhouse-0.0.1.dist-info/top_level.txt
py_solarhouse-0.0.1.dist-info/RECORD
