Metadata-Version: 2.1
Name: py-solarhouse
Version: 0.0.1
Summary: package for calculate solar power what you can get                on surfaces of building by solar heat collectors
Home-page: https://github.com/yaricp/py-solarhouse
Author: Yaric Pisarev
Author-email: yaricp@gmail.com
License: UNKNOWN
Platform: UNKNOWN
Classifier: Programming Language :: Python :: 3
Classifier: License :: OSI Approved :: MIT License
Classifier: Operating System :: OS Independent
Requires-Python: >=3.6
